httpimport.py
httpimport-1.4.1.dist-info/LICENSE
httpimport-1.4.1.dist-info/METADATA
httpimport-1.4.1.dist-info/WHEEL
httpimport-1.4.1.dist-info/top_level.txt
httpimport-1.4.1.dist-info/RECORD
